find_class/__init__.py
find_class/find_class.py
find_class-0.0.1.dist-info/LICENSE
find_class-0.0.1.dist-info/METADATA
find_class-0.0.1.dist-info/WHEEL
find_class-0.0.1.dist-info/top_level.txt
find_class-0.0.1.dist-info/RECORD
